sre_yield_mod
