Metadata-Version: 1.1
Name: tcore
Version: 0.2.2
Summary: theCore C++ embedded framework CLI tools
Home-page: https://github.com/theCore-embedded/tcore_cli
Author: Max Payne
Author-email: forgge@gmail.com
License: MPL
Download-URL: https://github.com/theCore-embedded/tcore_cli/archive/v0.2.2.tar.gz
Keywords: embedded,cpp,c++,the_core
Platform: UNKNOWN
